ui_setup/constants.py
ui_setup/onboarding.py
ui_setup/start.py
ui_setup/features/clone_ui/__init__.py
ui_setup/features/clone_ui/constants.py
ui_setup/features/clone_ui/tools.py
ui_setup/tools/__init__.py
ui_setup/ui/__init__.py
ui_setup-0.1.2.dist-info/licenses/LICENSE
ui_setup-0.1.2.dist-info/METADATA
ui_setup-0.1.2.dist-info/WHEEL
ui_setup-0.1.2.dist-info/entry_points.txt
ui_setup-0.1.2.dist-info/top_level.txt
ui_setup-0.1.2.dist-info/RECORD
