Metadata-Version: 2.4
Name: ui-setup
Version: 0.1.2
Summary: If you want to vibe code, at least do it properly.
Author: Joaquim Cassano
License: MIT
Requires-Python: >=3.7
License-File: LICENSE
Dynamic: license-file
